pyrdp-0.1.6.dist-info/METADATA
pyrdp-0.1.6.dist-info/WHEEL
pyrdp-0.1.6.dist-info/licenses/LICENSE
pyrdp/__init__.py
pyrdp-0.1.6.dist-info/RECORD
