Metadata-Version: 2.1
Name: pyrdp
Version: 0.1.6
Summary: Simple Rammer-Douglas-Peuker algorithm implementation.
Author-Email: Florian Stasse <f.stasse@skipperndt.com>
License: MIT
Project-URL: Repository, https://github.com/FlorianStasse/rdp-algo/
Requires-Python: >=3.8
Requires-Dist: numpy>=1.23.4
